sha256sum/__init__.py
sha256sum/py.typed
sha256sum-2022.6.11.dist-info/LICENSE
sha256sum-2022.6.11.dist-info/METADATA
sha256sum-2022.6.11.dist-info/WHEEL
sha256sum-2022.6.11.dist-info/top_level.txt
sha256sum-2022.6.11.dist-info/RECORD
