Metadata-Version: 2.1
Name: sha256sum
Version: 2022.6.11
Summary: Compute SHA256 message digest from a file
Home-page: https://github.com/oittaa/sha256sum
Author: Oittaa
Author-email: 
Keywords: sha256sum,SHA256
Classifier: Development Status :: 5 - Production/Stable
Classifier: Intended Audience :: Developers
Classifier: License :: OSI Approved :: MIT License
Classifier: Operating System :: OS Independent
Classifier: Programming Language :: Python
Classifier: Programming Language :: Python :: 3
Classifier: Programming Language :: Python :: 3.7
Classifier: Programming Language :: Python :: 3.8
Classifier: Programming Language :: Python :: 3.9
Classifier: Programming Language :: Python :: 3.10
Requires-Python: >=3.7
License-File: LICENSE
